Metadata-Version: 1.0
Name: textchange
Version: 0.0.9
Summary: This library can change text.
Home-page: UNKNOWN
Author: Yanwentao
Author-email: 3504802487@qq.com
License: UNKNOWN
Platform: UNKNOWN
